psh_environ/__init__.py
psh_environ/decoder.py
psh_environ/getenv.py
psh_environ-0.0.2.dist-info/AUTHORS
psh_environ-0.0.2.dist-info/LICENSE
psh_environ-0.0.2.dist-info/METADATA
psh_environ-0.0.2.dist-info/WHEEL
psh_environ-0.0.2.dist-info/pbr.json
psh_environ-0.0.2.dist-info/top_level.txt
psh_environ-0.0.2.dist-info/RECORD
